xc_rsa_util/__init__.py
xc_rsa_util/xc_rsa_util.py
xc_util-0.1.5.dist-info/licenses/LICENSE
xc_util-0.1.5.dist-info/METADATA
xc_util-0.1.5.dist-info/WHEEL
xc_util-0.1.5.dist-info/top_level.txt
xc_util-0.1.5.dist-info/RECORD
