Metadata-Version: 2.4
Name: xc-util
Version: 0.1.5
Requires-Python: >=3.7
License-File: LICENSE
Requires-Dist: cryptography>=36.0.0
Dynamic: license-file
Dynamic: requires-dist
Dynamic: requires-python
